[
   {
      "id": "954e2874-8a12-4fe9-b49d-f0d9ec6fb805",
      "name": "REMERA BOMB",
      "description": "Remera color gris de algodon, estampado de frente y espalda lisa, apto para lavadoras con agua fria y sin centrifugar",
      "category": "REMERAS",
      "sizes": "S, M, L, XL",
      "colors": "Gris",
      "precio": "$9.999",
      "mainImage": "1706131330166_products.webp",
      "images": []
   },
   {
      "id": "cf2b82e1-9483-4fe3-920c-319218d86fd5",
      "name": "REMERA CLASS",
      "description": "Remera color Blanca de algodon, estampado de frente y espalda, apto para lavadoras con agua fria y sin centrifugar",
      "category": "REMERAS",
      "sizes": "S, M, L, XL",
      "colors": "Blanco",
      "precio": "$23.000",
      "mainImage": "1706131520548_products.webp",
      "images": []
   }
]